{"associatedOccurrences":"herbariumSpecimenDuplicate: https://swbiodiversity.org/seinet/collections/individual/index.php?guid=e2b7cf70-7cbf-4bb8-b530-7fab24abdb7a","associatedTaxa":"Pinus edulis, Juniperus scopulorum, Mirabilis, Boechera, Opuntia, Echinocereus, Yucca.","basisOfRecord":"PreservedSpecimen","catalogNumber":"ASC00124714","collectionID":"17a53c97-835b-409e-8a9a-c9a7307a4965","coordinateUncertaintyInMeters":"22","country":"United States","county":"Huerfano","decimalLatitude":"37.839455","decimalLongitude":"-105.332484","eventDate":"2021-07-10","extensions":{"http://rs.iobis.org/obis/terms/ExtendedMeasurementOrFact":[],"ac:Multimedia":[{"MetadataDate":"2023-01-12 07:41:57","Owner":"Deaver Herbarium","UsageTerms":"CC BY-NC-SA (Attribution-NonCommercial-ShareAlike)","accessURI":"https://swbiodiversity.org/imglib/seinet/swnode/ASC/ASC00124/ASC00124714_lg.jpg","associatedSpecimenReference":"https://swbiodiversity.org/seinet/collections/individual/index.php?occid=29015134","format":"image/jpeg","goodQualityAccessURI":"https://swbiodiversity.org/imglib/seinet/swnode/ASC/ASC00124/ASC00124714.jpg","identifier":"https://swbiodiversity.org/imglib/seinet/swnode/ASC/ASC00124/ASC00124714_lg.jpg","metadataLanguage":"en","providerManagedID":"urn:uuid:fb09250f-e634-42b9-881d-3fabd48fb693","rights":"http://creativecommons.org/licenses/by/3.0/","subtype":"Photograph","thumbnailAccessURI":"https://swbiodiversity.org/imglib/seinet/swnode/ASC/ASC00124/ASC00124714_tn.jpg","type":"StillImage"}],"dwc:Identification":[{"dateIdentified":"s.d.","genus":"Physalis","identifiedBy":"unknown","modified":"2023-07-16 05:07:11","recordID":"urn:uuid:0f949ebe-cd11-4b26-9f32-1d531c09523c","scientificName":"Physalis virginiana","scientificNameAuthorship":"Mill.","specificEpithet":"virginiana","tidInterpreted":"11024"}]},"family":"Solanaceae","genus":"Physalis","geodeticDatum":"WGS84","habitat":"Pinyon-Juniper Woodland.; Pierre shale; Niobrara Formation; Carlile Formation; Greenhorn Formation; Graneros Shale.","higherClassification":"Plantae|Spermatophyta|Tracheophyta|Magnoliophyta|Eudicots|Core Eudicots|Lamiids|Asterids|Solanales|Solanaceae|Physalis","id":"29015134","institutionCode":"ASC","kingdom":"Plantae","locality":"Navajo Nation Ranch. Wolf Springs Ranch. Mesa/Rock outcrop SE of Creager Reservoir. Atop the Mesa, on S facing slope. 90 yds. N of CR 559.","minimumElevationInMeters":"2413","modified":"2023-07-16 07:02:03","occurrenceID":"eae4379b-4da6-49af-abef-d99a684a5e2d","order":"Solanales","phylum":"Magnoliophyta","recordEnteredBy":"giselak","recordID":"eae4379b-4da6-49af-abef-d99a684a5e2d","recordNumber":"425","recordedBy":"Tsinigine, Adriano; Begay, Reggie","references":"https://swbiodiversity.org/seinet/collections/individual/index.php?occid=29015134","rights":"http://creativecommons.org/licenses/by/3.0/","rightsHolder":"Deaver Herbarium","scientificName":"Physalis virginiana","scientificNameAuthorship":"Mill.","specificEpithet":"virginiana","stateProvince":"Colorado","taxonID":"11024","taxonRank":"Species","verbatimElevation":"7,917 ft."}